dask_optuna/__init__.py
dask_optuna/_version.py
dask_optuna/serialize.py
dask_optuna/storage.py
dask_optuna/tests/__init__.py
dask_optuna/tests/test_storage.py
dask_optuna/tests/utils.py
dask_optuna-0.0.2.dist-info/LICENSE
dask_optuna-0.0.2.dist-info/METADATA
dask_optuna-0.0.2.dist-info/WHEEL
dask_optuna-0.0.2.dist-info/top_level.txt
dask_optuna-0.0.2.dist-info/RECORD
