Metadata-Version: 2.1
Name: dask-optuna
Version: 0.0.2
Summary: Scaling Optuna with Dask
Home-page: https://github.com/jrbourbeau/dask-optuna
Author: James Bourbeau
License: MIT
Project-URL: Documentation, https://jrbourbeau.github.io/dask-optuna
Project-URL: Source Code, https://github.com/jrbourbeau/dask-optuna
Project-URL: Issue Tracker, https://github.com/jrbourbeau/dask-optuna/issues
Keywords: optuna,dask,distributed
Platform: UNKNOWN
Classifier: Development Status :: 4 - Beta
Classifier: License :: OSI Approved :: MIT License
Classifier: Programming Language :: Python :: 3
Classifier: Programming Language :: Python :: 3.6
Classifier: Programming Language :: Python :: 3.7
Classifier: Programming Language :: Python :: 3.8
Requires-Python: >=3.6
Requires-Dist: optuna (>=2.1.0)
Requires-Dist: dask
Requires-Dist: distributed
